gj/__init__.py
gj/__main__.py
gj/backups.py
gj/follow.py
gj/packages.py
gj/readinglist.py
gj/utils.py
gj-0.6.1.dist-info/LICENSE
gj-0.6.1.dist-info/METADATA
gj-0.6.1.dist-info/WHEEL
gj-0.6.1.dist-info/top_level.txt
gj-0.6.1.dist-info/RECORD
