Metadata-Version: 2.1
Name: gj
Version: 0.6.1
Summary: Disk and file-based cache
Home-page: http://www.grantjenks.com/docs/gj/
Author: Grant Jenks
Author-email: contact@grantjenks.com
License: Apache 2.0
Keywords: grant jenks tools
Platform: UNKNOWN
Classifier: Development Status :: 4 - Beta
Classifier: Intended Audience :: Developers
Classifier: License :: OSI Approved :: Apache Software License
Classifier: Natural Language :: English
Classifier: Programming Language :: Python
Classifier: Programming Language :: Python :: 2
Classifier: Programming Language :: Python :: 2.7
Classifier: Programming Language :: Python :: Implementation :: CPython
